{
    "curveShape1": {
        "degree": 1, 
        "form": 0, 
        "min": 0.0, 
        "max": 16.0, 
        "spans": 16, 
        "cv_len": 17, 
        "cv_pose": [
            [
                -1.0, 
                1.0, 
                -1.0
            ], 
            [
                1.0, 
                1.0, 
                -1.0
            ], 
            [
                1.0, 
                1.0, 
                1.0
            ], 
            [
                -1.0, 
                1.0, 
                1.0
            ], 
            [
                -1.0, 
                1.0, 
                -1.0
            ], 
            [
                -1.0, 
                -1.0, 
                -1.0
            ], 
            [
                1.0, 
                -1.0, 
                -1.0
            ], 
            [
                1.0, 
                1.0, 
                -1.0
            ], 
            [
                1.0, 
                1.0, 
                1.0
            ], 
            [
                1.0, 
                -1.0, 
                1.0
            ], 
            [
                1.0, 
                -1.0, 
                -1.0
            ], 
            [
                -1.0, 
                -1.0, 
                -1.0
            ], 
            [
                -1.0, 
                -1.0, 
                1.0
            ], 
            [
                1.0, 
                -1.0, 
                1.0
            ], 
            [
                1.0, 
                1.0, 
                1.0
            ], 
            [
                -1.0, 
                1.0, 
                1.0
            ], 
            [
                -1.0, 
                -1.0, 
                1.0
            ]
        ]
    }
}