{
    "polyToCurveShape43": {
        "min": 0.0,
        "max": 80.0,
        "spans": 80,
        "degree": 1,
        "form": 2,
        "cv_len": 80,
        "cv_pose": [
            [
                -0.8467788696289062,
                5.185483932495117,
                0.0
            ],
            [
                -0.9406509399414062,
                5.1824188232421875,
                0.0
            ],
            [
                -1.0283889770507812,
                5.173386573791504,
                0.0
            ],
            [
                -1.1099929809570312,
                5.158225059509277,
                0.0
            ],
            [
                -1.1854782104492188,
                5.137096405029297,
                0.0
            ],
            [
                -1.2591934204101562,
                5.106773376464844,
                0.0
            ],
            [
                -1.3346786499023438,
                5.064516067504883,
                0.0
            ],
            [
                -1.4124221801757812,
                5.010000228881836,
                0.0
            ],
            [
                -1.4919357299804688,
                4.943548202514648,
                0.0
            ],
            [
                -2.2390365600585938,
                4.123387336730957,
                0.0
            ],
            [
                -2.8991928100585938,
                3.2761287689208984,
                0.0
            ],
            [
                -3.4729080200195312,
                2.401613235473633,
                0.0
            ],
            [
                -3.9596786499023438,
                1.5,
                0.0
            ],
            [
                -4.347908020019531,
                0.5920963287353516,
                0.0
            ],
            [
                -4.625007629394531,
                -0.30048370361328125,
                0.0
            ],
            [
                -4.791450500488281,
                -1.1780643463134766,
                0.0
            ],
            [
                -4.846778869628906,
                -2.040323257446289,
                0.0
            ],
            [
                -4.816612243652344,
                -2.522258758544922,
                0.0
            ],
            [
                -4.725807189941406,
                -2.967742919921875,
                0.0
            ],
            [
                -4.574684143066406,
                -3.3770980834960938,
                0.0
            ],
            [
                -4.362907409667969,
                -3.75,
                0.0
            ],
            [
                -4.102897644042969,
                -4.083227157592773,
                0.0
            ],
            [
                -3.8064498901367188,
                -4.373064041137695,
                0.0
            ],
            [
                -3.4738693237304688,
                -4.619516372680664,
                0.0
            ],
            [
                -3.1048355102539062,
                -4.822580337524414,
                0.0
            ],
            [
                -2.7117691040039062,
                -4.981452941894531,
                0.0
            ],
            [
                -2.3064498901367188,
                -5.094839096069336,
                0.0
            ],
            [
                -1.8891983032226562,
                -5.16290283203125,
                0.0
            ],
            [
                -1.4596786499023438,
                -5.185483932495117,
                0.0
            ],
            [
                -0.7117691040039062,
                -5.127098083496094,
                0.0
            ],
            [
                0.03226470947265625,
                -4.95161247253418,
                0.0
            ],
            [
                0.7721023559570312,
                -4.659355163574219,
                0.0
            ],
            [
                1.5080642700195312,
                -4.25,
                0.0
            ],
            [
                2.2085494995117188,
                -3.7461299896240234,
                0.0
            ],
            [
                2.8427352905273438,
                -3.1693553924560547,
                0.0
            ],
            [
                3.4101638793945312,
                -2.520162582397461,
                0.0
            ],
            [
                3.9112930297851562,
                -1.7983875274658203,
                0.0
            ],
            [
                4.320487976074219,
                -1.0312910079956055,
                0.0
            ],
            [
                4.612907409667969,
                -0.24612903594970703,
                0.0
            ],
            [
                4.788230895996094,
                0.5574188232421875,
                0.0
            ],
            [
                4.846778869628906,
                1.3790321350097656,
                0.0
            ],
            [
                4.812416076660156,
                1.791773796081543,
                0.0
            ],
            [
                4.709678649902344,
                2.191451072692871,
                0.0
            ],
            [
                4.538230895996094,
                2.57806396484375,
                0.0
            ],
            [
                4.298393249511719,
                2.951613426208496,
                0.0
            ],
            [
                3.9928970336914062,
                3.301774024963379,
                0.0
            ],
            [
                3.6249923706054688,
                3.618870735168457,
                0.0
            ],
            [
                3.1945114135742188,
                3.902581214904785,
                0.0
            ],
            [
                2.7016067504882812,
                4.153225898742676,
                0.0
            ],
            [
                2.4893569946289062,
                4.2332258224487305,
                0.0
            ],
            [
                2.2237167358398438,
                4.312419891357422,
                0.0
            ],
            [
                1.9046707153320312,
                4.390483856201172,
                0.0
            ],
            [
                1.5322647094726562,
                4.467741966247559,
                0.0
            ],
            [
                1.1537094116210938,
                4.534677505493164,
                0.0
            ],
            [
                0.8164443969726562,
                4.58258056640625,
                0.0
            ],
            [
                0.5206375122070312,
                4.61129093170166,
                0.0
            ],
            [
                0.26612091064453125,
                4.620967864990234,
                0.0
            ],
            [
                0.08112335205078125,
                4.619355201721191,
                0.0
            ],
            [
                -0.07064056396484375,
                4.614838600158691,
                0.0
            ],
            [
                -0.18903350830078125,
                4.607257843017578,
                0.0
            ],
            [
                -0.27419281005859375,
                4.596774101257324,
                0.0
            ],
            [
                -0.34032440185546875,
                4.586129188537598,
                0.0
            ],
            [
                -0.40129852294921875,
                4.578548431396484,
                0.0
            ],
            [
                -0.45725250244140625,
                4.574031829833984,
                0.0
            ],
            [
                -0.5080642700195312,
                4.572580337524414,
                0.0
            ],
            [
                -0.49758148193359375,
                4.594193458557129,
                0.0
            ],
            [
                -0.48194122314453125,
                4.626935005187988,
                0.0
            ],
            [
                -0.46129608154296875,
                4.670806884765625,
                0.0
            ],
            [
                -0.43547821044921875,
                4.72580623626709,
                0.0
            ],
            [
                -0.41080474853515625,
                4.782742500305176,
                0.0
            ],
            [
                -0.39322662353515625,
                4.83258056640625,
                0.0
            ],
            [
                -0.38257598876953125,
                4.875483512878418,
                0.0
            ],
            [
                -0.37903594970703125,
                4.911290168762207,
                0.0
            ],
            [
                -0.38871002197265625,
                4.965644836425781,
                0.0
            ],
            [
                -0.41742706298828125,
                5.016129493713379,
                0.0
            ],
            [
                -0.46532440185546875,
                5.0624189376831055,
                0.0
            ],
            [
                -0.5322647094726562,
                5.104839324951172,
                0.0
            ],
            [
                -0.6095199584960938,
                5.1399993896484375,
                0.0
            ],
            [
                -0.6875839233398438,
                5.165323257446289,
                0.0
            ],
            [
                -0.7667770385742188,
                5.180322647094727,
                0.0
            ]
        ]
    },
    "polyToCurveShape60": {
        "min": 0.0,
        "max": 61.0,
        "spans": 61,
        "degree": 1,
        "form": 2,
        "cv_len": 61,
        "cv_pose": [
            [
                -0.6816482543945312,
                4.341048240661621,
                0.0
            ],
            [
                -0.6896743774414062,
                4.320987701416016,
                0.0
            ],
            [
                -0.6977005004882812,
                4.292903900146484,
                0.0
            ],
            [
                -0.7057266235351562,
                4.256793975830078,
                0.0
            ],
            [
                -0.7137527465820312,
                4.2126617431640625,
                0.0
            ],
            [
                -0.7208175659179688,
                4.163392066955566,
                0.0
            ],
            [
                -0.7257919311523438,
                4.112359046936035,
                0.0
            ],
            [
                -0.7288284301757812,
                4.059078216552734,
                0.0
            ],
            [
                -0.7298049926757812,
                4.004032135009766,
                0.0
            ],
            [
                -0.6816482543945312,
                3.8636083602905273,
                0.0
            ],
            [
                -0.5372238159179688,
                3.7633066177368164,
                0.0
            ],
            [
                -0.29648590087890625,
                3.703125,
                0.0
            ],
            [
                0.04051971435546875,
                3.6830644607543945,
                0.0
            ],
            [
                0.6343154907226562,
                3.699112892150879,
                0.0
            ],
            [
                0.8167800903320312,
                3.7130746841430664,
                0.0
            ],
            [
                0.9793472290039062,
                3.7231855392456055,
                0.0
            ],
            [
                1.1216964721679688,
                3.729123115539551,
                0.0
            ],
            [
                1.2441482543945312,
                3.7312097549438477,
                0.0
            ],
            [
                1.5821304321289062,
                3.718050003051758,
                0.0
            ],
            [
                1.8900985717773438,
                3.6790523529052734,
                0.0
            ],
            [
                2.1679000854492188,
                3.6137351989746094,
                0.0
            ],
            [
                2.4156875610351562,
                3.522580146789551,
                0.0
            ],
            [
                2.8148117065429688,
                3.31732177734375,
                0.0
            ],
            [
                3.1619338989257812,
                3.0871877670288086,
                0.0
            ],
            [
                3.4567489624023438,
                2.831857681274414,
                0.0
            ],
            [
                3.6995620727539062,
                2.5516529083251953,
                0.0
            ],
            [
                3.8890914916992188,
                2.2371044158935547,
                0.0
            ],
            [
                4.024543762207031,
                1.879547119140625,
                0.0
            ],
            [
                4.105735778808594,
                1.4788179397583008,
                0.0
            ],
            [
                4.132865905761719,
                1.0350799560546875,
                0.0
            ],
            [
                4.082145690917969,
                0.3669862747192383,
                0.0
            ],
            [
                3.9301681518554688,
                -0.2889118194580078,
                0.0
            ],
            [
                3.6769332885742188,
                -0.9329338073730469,
                0.0
            ],
            [
                3.3224258422851562,
                -1.56475830078125,
                0.0
            ],
            [
                2.8870315551757812,
                -2.160634994506836,
                0.0
            ],
            [
                2.3916091918945312,
                -2.696168899536133,
                0.0
            ],
            [
                1.8358535766601562,
                -3.1716842651367188,
                0.0
            ],
            [
                1.2200851440429688,
                -3.586854934692383,
                0.0
            ],
            [
                0.5705947875976562,
                -3.9238719940185547,
                0.0
            ],
            [
                -0.08594512939453125,
                -4.1645965576171875,
                0.0
            ],
            [
                -0.7493820190429688,
                -4.309032440185547,
                0.0
            ],
            [
                -1.4198837280273438,
                -4.357177734375,
                0.0
            ],
            [
                -1.9822158813476562,
                -4.318662643432617,
                0.0
            ],
            [
                -2.4811630249023438,
                -4.202793121337891,
                0.0
            ],
            [
                -2.9170303344726562,
                -4.009729385375977,
                0.0
            ],
            [
                -3.2895126342773438,
                -3.7393150329589844,
                0.0
            ],
            [
                -3.5880203247070312,
                -3.3838424682617188,
                0.0
            ],
            [
                -3.8011398315429688,
                -2.934968948364258,
                0.0
            ],
            [
                -3.9290390014648438,
                -2.392854690551758,
                0.0
            ],
            [
                -3.9715805053710938,
                -1.7573394775390625,
                0.0
            ],
            [
                -3.9269638061523438,
                -1.0221624374389648,
                0.0
            ],
            [
                -3.7931137084960938,
                -0.27687549591064453,
                0.0
            ],
            [
                -3.5698776245117188,
                0.4783620834350586,
                0.0
            ],
            [
                -3.2574234008789062,
                1.2437095642089844,
                0.0
            ],
            [
                -2.8627853393554688,
                2.0029592514038086,
                0.0
            ],
            [
                -2.3928909301757812,
                2.7402219772338867,
                0.0
            ],
            [
                -1.8477249145507812,
                3.4553375244140625,
                0.0
            ],
            [
                -1.2273025512695312,
                4.148468017578125,
                0.0
            ],
            [
                -1.1149673461914062,
                4.232561111450195,
                0.0
            ],
            [
                -0.9865798950195312,
                4.292903900146484,
                0.0
            ],
            [
                -0.8422927856445312,
                4.329011917114258,
                0.0
            ]
        ]
    }
}